protos_pb2.py
protos_pb2_grpc.py
tickstore_grpc-1.0.3.dist-info/METADATA
tickstore_grpc-1.0.3.dist-info/WHEEL
tickstore_grpc-1.0.3.dist-info/top_level.txt
tickstore_grpc-1.0.3.dist-info/RECORD
