Metadata-Version: 2.1
Name: tickstore-grpc
Version: 1.0.3
Summary: grpc bindings
Author: Alphaticks
License: copyright
